[1,["209pHeM25BxLsVJl/rqGsO@d90a4","c4ukyjBq9Nf61GpSTHVnTf@6c48a","9bIKUUbMNJ3rIWtrhjBGJJ","a3Ta3RUw1B4psEBXWFqc8a","62C2vzA2lFYIN/KiwAtzwm","12Y9dMgWdJKJGmTiZyQR9H@a804a","beDSR5AZNFHIjYsREIzr6D@6c48a","f6SJZOjTJB/JrJeh5xTdF7","209pHeM25BxLsVJl/rqGsO@6976d","209pHeM25BxLsVJl/rqGsO@cea3d","209pHeM25BxLsVJl/rqGsO@75571","209pHeM25BxLsVJl/rqGsO@b0db1","209pHeM25BxLsVJl/rqGsO@7da37","209pHeM25BxLsVJl/rqGsO@a82d6","04/AOf9+xBpIQwtB3qYp0m@6c48a","209pHeM25BxLsVJl/rqGsO@fcb77","5eOzfHwx5Cd7p+FSsLzOc3","1amd06FYdFC6wP6gjlBKaR","09nMmb/y5DyqdL9o62Qty+","cfomTEdYBOKIVITww0r9F3"],["node","_parent","_mesh","value","_effectAsset","normalMap","targetInfo","mainTexture","root","data","gridRootPosition","scene","asset"],[["cc.Node",["_name","_id","_objFlags","__editorExtras__","_parent","_components","_children","_lpos","_prefab","_lrot","_euler"],-1,1,9,2,5,4,5,5],["cc.Node",["_name","_children","_lpos","_parent","_components","_lrot","_euler"],2,9,5,1,9,5,5],["cc.MeshRenderer",["_name","node","_materials","bakeSettings","_mesh","__prefab"],2,1,3,4,6,4],["cc.Material",["_name","_states","_defines","_props"],0,12],["cc.Mesh",["_native","_hash","_struct"],1,11],["cc.Prefab",[],3],["cc.PrefabInfo",["fileId","instance","targetOverrides","nestedPrefabInstanceRoots","root","asset"],-1,1,1],["cc.PrefabInfo",["root","asset","fileId","instance","targetOverrides","nestedPrefabInstanceRoots"],-2,2],["cc.PrefabInfo",["fileId","targetOverrides","nestedPrefabInstanceRoots","root","instance","asset"],0,1,4,6],["cc.CompPrefabInfo",["fileId"],2],["cc.ModelBakeSettings",[],3],["cc.SceneAsset",["_name"],2],["ab602wfEZlBcZIwNt85bToP",["node"],3,1],["cc.Scene",["_name","_children","_prefab","_globals"],2,2,4,4],["cc.SceneGlobals",["ambient","shadows","_skybox","fog","octree","lightProbeInfo"],3,4,4,4,4,4,4],["cc.AmbientInfo",["_skyIllumLDR","_skyColorHDR","_skyColorLDR","_groundAlbedoLDR"],2,5,5,5],["cc.ShadowsInfo",["_enabled","_shadowColor"],2,5],["cc.SkyboxInfo",[],3],["cc.FogInfo",[],3],["cc.OctreeInfo",[],3],["cc.LightProbeInfo",[],3],["cc.TargetInfo",["localID"],2],["85530I7QMxNc6fSEzbqkH22",["node"],3,1],["4bbadlgznNHLbYQU/wQ6MXf",["node"],3,1],["88cabtAq8tBtaEF/OL2a/gl",["node"],3,1],["75dffdeWhpJnqUjoRlYbD0S",["node"],3,1],["cc.PrefabInstance",["fileId","prefabRootNode","propertyOverrides"],1,9],["CCPropertyOverrideInfo",["value","propertyPath","targetInfo"],1,1],["CCPropertyOverrideInfo",["propertyPath","targetInfo","value"],2,1,8],["CCPropertyOverrideInfo",["propertyPath","targetInfo","value"],2,1,6],["CCPropertyOverrideInfo",["propertyPath","targetInfo","value"],2,4,6],["CCPropertyOverrideInfo",["propertyPath","targetInfo","value"],2,4,8],["31d13hnm6lHOrKruwhIfP1z",["node","gridRootPosition","gridSize"],3,1,1,8],["1b793PhIJ9NWoo2f07TGDdv",["node"],3,1],["cc.Camera",["_projection","_fov","_near","_visibility","node"],-1,1],["90b9diPA3hE7b9yuxvreLOr",["node"],3,1],["cc.DirectionalLight",["node","_color","_staticSettings"],3,1,5,4],["cc.StaticLightSettings",[],3],["79614oMmf9IxbI3/sotKGqU",["node"],3,1],["546e8g2HjdHMYNP/4gFPvFU",["node"],3,1]],[[0,0,4,7,2],[21,0,2],[0,0,4,5,7,2],[38,0,1],[10,1],[4,0,1,2,3],[0,0,4,7,9,10,2],[1,0,3,1,2,2],[6,0,1,2,3,4,5,5],[0,0,4,6,2],[2,1,5,2,3,4,1],[9,0,2],[31,0,1,2,2],[3,0,1,2,3,4],[0,0,4,5,8,2],[30,0,1,2,2],[23,0,1],[1,0,3,1,4,2,2],[22,0,1],[27,0,1,2,3],[28,0,1,2,2],[1,0,3,1,4,2,5,6,2],[1,0,1,4,2,2],[2,0,1,2,3,4,2],[24,0,1],[5,1],[0,0,6,8,2],[0,0,4,5,8,7,2],[0,0,6,2],[0,0,6,5,2],[0,0,1,4,6,3],[0,0,1,4,6,5,7,3],[0,2,3,8,3],[0,0,1,4,6,5,7,9,10,3],[0,0,4,5,7,9,10,2],[0,0,1,4,5,9,10,3],[0,0,4,5,2],[7,0,1,2,3,4,5,6],[8,0,1,2,3,4,5,4],[11,0,2],[12,0,1],[13,0,1,2,3,2],[14,0,1,2,3,4,5,1],[15,0,1,2,3,2],[16,0,1,2],[17,1],[18,1],[19,1],[20,1],[25,0,1],[26,0,1,2,3],[29,0,1,2,2],[32,0,1,2,1],[33,0,1],[34,0,1,2,3,4,5],[35,0,1],[36,0,1,2,1],[37,1],[39,0,1]],[[[[13,"Level3_Sence4",[{"rasterizerState":{},"depthStencilState":{},"blendState":{"targets":[{}]}},{"rasterizerState":{},"depthStencilState":{},"blendState":{"targets":[{}]}},{"rasterizerState":{},"depthStencilState":{},"blendState":{"targets":[{}]}},{"rasterizerState":{},"depthStencilState":{},"blendState":{"targets":[{}]}}],[{"USE_POSITION_SCALING":true},{"USE_BASE_COLOR_MAP":true,"BASE_COLOR_MAP_AS_SHADE_MAP_1":true,"BASE_COLOR_MAP_AS_SHADE_MAP_2":true},{},{}],[[{},[{},"mainColor",8,[4,4294947503],"specular",8,[4,16777215],"normalMap",6,0,"mainTexture",6,1],{},{}],0,11,0,0]]],0,0,[0,0,0],[5,7,4],[1,6,2]],[[[5,".bin",2531713262,[{"primitives":[{"primitiveMode":7,"vertexBundelIndices":[0],"indexView":{"offset":1344,"length":72,"count":36,"stride":2}}],"vertexBundles":[{"view":{"offset":0,"length":1344,"count":24,"stride":56},"attributes":[{"name":"a_position","format":32,"isNormalized":false},{"name":"a_normal","format":32,"isNormalized":false},{"name":"a_texCoord","format":21,"isNormalized":false},{"name":"a_tangent","format":44,"isNormalized":false},{"name":"a_texCoord1","format":21,"isNormalized":false}]}]},"minPosition",8,[1,-0.5,-0.5,-0.5],"maxPosition",8,[1,0.5,0.5,0.5]]],-1],0,0,[],[],[]],[[[13,"Level1_Sence2",[{"rasterizerState":{},"depthStencilState":{},"blendState":{"targets":[{}]}},{"rasterizerState":{},"depthStencilState":{},"blendState":{"targets":[{}]}},{"rasterizerState":{},"depthStencilState":{},"blendState":{"targets":[{}]}},{"rasterizerState":{},"depthStencilState":{},"blendState":{"targets":[{}]}}],[{"USE_POSITION_SCALING":true},{"USE_BASE_COLOR_MAP":true,"BASE_COLOR_MAP_AS_SHADE_MAP_1":true,"BASE_COLOR_MAP_AS_SHADE_MAP_2":true},{},{}],[[{},[{},"mainColor",8,[4,4294429104],"specular",8,[4,16777215],"normalMap",6,0],{},{}],0,11,0,0]]],0,0,[0,0],[5,4],[1,2]],[[[5,".bin",535126109,[{"primitives":[{"primitiveMode":7,"vertexBundelIndices":[0],"indexView":{"offset":192,"length":12,"count":6,"stride":2}}],"vertexBundles":[{"view":{"offset":0,"length":192,"count":4,"stride":48},"attributes":[{"name":"a_position","format":32,"isNormalized":false},{"name":"a_normal","format":32,"isNormalized":false},{"name":"a_texCoord","format":21,"isNormalized":false},{"name":"a_tangent","format":44,"isNormalized":false}]}]},"minPosition",8,[1,-3.5,-1.7484555314695172e-7,-1.9999995231628418],"maxPosition",8,[1,3.5,1.7484551051438757e-7,2]]],-1],0,0,[],[],[]],[[[5,".bin",2589106269,[{"primitives":[{"primitiveMode":7,"vertexBundelIndices":[0],"indexView":{"offset":576,"length":36,"count":18,"stride":2}}],"vertexBundles":[{"view":{"offset":0,"length":576,"count":12,"stride":48},"attributes":[{"name":"a_position","format":32,"isNormalized":false},{"name":"a_normal","format":32,"isNormalized":false},{"name":"a_texCoord","format":21,"isNormalized":false},{"name":"a_tangent","format":44,"isNormalized":false}]}]},"minPosition",8,[1,-15,-5.245366310191457e-7,-9.5],"maxPosition",8,[1,15,4.1525819938215136e-7,12]]],-1],0,0,[],[],[]],[[[5,".bin",2760633329,[{"primitives":[{"primitiveMode":7,"vertexBundelIndices":[0],"indexView":{"offset":355248,"length":34914,"count":17457,"stride":2}}],"vertexBundles":[{"view":{"offset":0,"length":355248,"count":7401,"stride":48},"attributes":[{"name":"a_position","format":32,"isNormalized":false},{"name":"a_normal","format":32,"isNormalized":false},{"name":"a_texCoord","format":21,"isNormalized":false},{"name":"a_tangent","format":44,"isNormalized":false}]}]},"minPosition",8,[1,-15,-0.6426689624786377,-9.36589527130127],"maxPosition",8,[1,15,6.676004886627197,17.10936737060547]]],-1],0,0,[],[],[]],[[[5,".bin",1483615794,[{"primitives":[{"primitiveMode":7,"vertexBundelIndices":[0],"indexView":{"offset":192,"length":12,"count":6,"stride":2}}],"vertexBundles":[{"view":{"offset":0,"length":192,"count":4,"stride":48},"attributes":[{"name":"a_position","format":32,"isNormalized":false},{"name":"a_normal","format":32,"isNormalized":false},{"name":"a_texCoord","format":21,"isNormalized":false},{"name":"a_tangent","format":44,"isNormalized":false}]}]},"minPosition",8,[1,-15,-0.0000027538176254893187,-30],"maxPosition",8,[1,15,-0.0000026226832687825663,30]]],-1],0,0,[],[],[]],[[[5,".bin",10954155,[{"primitives":[{"primitiveMode":7,"vertexBundelIndices":[0],"indexView":{"offset":192,"length":12,"count":6,"stride":2}}],"vertexBundles":[{"view":{"offset":0,"length":192,"count":4,"stride":48},"attributes":[{"name":"a_position","format":32,"isNormalized":false},{"name":"a_normal","format":32,"isNormalized":false},{"name":"a_texCoord","format":21,"isNormalized":false},{"name":"a_tangent","format":44,"isNormalized":false}]}]},"minPosition",8,[1,-15,4.1525819938215136e-7,-15],"maxPosition",8,[1,15,6.556708171956416e-7,-9.5]]],-1],0,0,[],[],[]],[[[5,".bin",1882640399,[{"primitives":[{"primitiveMode":7,"vertexBundelIndices":[0],"indexView":{"offset":576,"length":48,"count":24,"stride":2}}],"vertexBundles":[{"view":{"offset":0,"length":576,"count":12,"stride":48},"attributes":[{"name":"a_position","format":32,"isNormalized":false},{"name":"a_normal","format":32,"isNormalized":false},{"name":"a_texCoord","format":21,"isNormalized":false},{"name":"a_tangent","format":44,"isNormalized":false}]}]},"minPosition",8,[1,-15,-2.18556948539117e-7,-8.5],"maxPosition",8,[1,15,3.715468039899861e-7,5]]],-1],0,0,[],[],[]],[[[13,"01 - Default",[{"rasterizerState":{},"blendState":{"targets":[{}]},"depthStencilState":{}}],[{"DCC_APP_NAME":1}],[[[{"albedoScale":1,"specularFactor":0,"shininessExponent":2.000000020657396,"emissiveScale":0},"mainColor",8,[4,4291480266],"specularColor",8,[4,4294177779],"emissive",8,[4,4278190080]]],11]]],0,0,[0],[4],[7]],[[[25],[26,"Level3_Scence",[-2,-3,-4,-5,-6,-7],[8,"e103AGfwxSC7kwvfROY7cZ",null,null,null,-1,0]],[14,"Level3_Scence2",1,[[10,-8,[11,"88FltwsJZUAo3E3x6WykKq"],[0],[4],1]],[8,"dbyyMsDoVfwprh1T0XdMDj",null,null,null,1,0]],[14,"Level3_Scence4",1,[[10,-9,[11,"a70TKS1dldZKdpAHws5h91"],[2],[4],3]],[8,"329dsfDy5fQqjIsBTm/ZhM",null,null,null,1,0]],[14,"Level3_Scence3",1,[[10,-10,[11,"a7oSkYTLhTTqcr5ZJobtrj"],[4],[4],5]],[8,"641Zmjnl1YtL7pdvwi4US5",null,null,null,1,0]],[14,"Level3_Scence5",1,[[10,-11,[11,"c2BXncYG9VobZJHlVXrHL3"],[6],[4],7]],[8,"ecd/gFgEVbZo9C5TOVB/wv",null,null,null,1,0]],[14,"Level3_Scence1",1,[[10,-12,[11,"4bUCtekHBZAbH7dB6ugq04"],[8],[4],9]],[8,"ac34y8yYhV161zw6bhE6GX",null,null,null,1,0]],[27,"Level3_Scence6",1,[[10,-13,[11,"266lxKbAdQtb3jA6lI5VQC"],[10],[4],11]],[8,"0dEiMpemRf+o65jMvQjbT6",null,null,null,1,0],[1,0,-0.5,0]]],0,[0,8,1,0,-1,2,0,-2,3,0,-3,4,0,-4,5,0,-5,6,0,-6,7,0,0,2,0,0,3,0,0,4,0,0,5,0,0,6,0,0,7,0,9,1,13],[0,0,0,0,0,0,0,0,0,0,0,0],[-1,2,-1,2,-1,2,-1,2,-1,2,-1,2],[0,8,0,9,0,10,0,11,0,12,0,13]],[[[13,"Grass1",[{"rasterizerState":{},"depthStencilState":{},"blendState":{"targets":[{}]}},{"rasterizerState":{},"depthStencilState":{},"blendState":{"targets":[{}]}},{"rasterizerState":{},"depthStencilState":{},"blendState":{"targets":[{}]}},{"rasterizerState":{},"depthStencilState":{},"blendState":{"targets":[{}]}}],[{"USE_POSITION_SCALING":true},{"USE_BASE_COLOR_MAP":true,"BASE_COLOR_MAP_AS_SHADE_MAP_1":true,"BASE_COLOR_MAP_AS_SHADE_MAP_2":true},{},{}],[[{},[{},"specular",8,[4,16777215],"normalMap",6,0,"mainTexture",6,1],{},{}],0,11,0,0]]],0,0,[0,0,0],[5,7,4],[1,14,2]],[[[13,"Water1",[{"rasterizerState":{},"depthStencilState":{},"blendState":{"targets":[{}]}},{"rasterizerState":{},"depthStencilState":{},"blendState":{"targets":[{}]}},{"rasterizerState":{},"depthStencilState":{},"blendState":{"targets":[{}]}},{"rasterizerState":{},"depthStencilState":{},"blendState":{"targets":[{}]}}],[{"USE_POSITION_SCALING":true},{"USE_BASE_COLOR_MAP":true,"BASE_COLOR_MAP_AS_SHADE_MAP_1":true,"BASE_COLOR_MAP_AS_SHADE_MAP_2":true},{},{}],[[[{},"baseColor",8,[4,4294912256]],[{},"specular",8,[4,16777215],"normalMap",6,0],{},{}],11,11,0,0]]],0,0,[0,0],[5,4],[1,2]],[[[39,"Level3"],[28,"Obstacles",[-1,-2,-3,-4,-5,-6,-7,-8,-9,-10]],[29,"Desktops",[-12,-13,-14,-15,-16,-17,-18],[[40,-11]]],[41,"Level3",[-20,-21,-22,-23],[37,null,null,"1b9067fa-ddb4-4b82-a79a-e5cc67c1425f",null,null,[-19]],[42,[43,0.8,[2,0.2,0.5,0.8,0.520833125],[2,0.452588,0.607642,0.755699,0],[2,0.618555,0.577848,0.544564,0]],[44,true,[4,893995337]],[45],[46],[47],[48]]],[30,"Level3","28YGCoehJA2ZVKxg0pEi+x",3,[-24,1,-25,-26]],[9,"Marker",4,[-27,2,-28,-29]],[1,["e103AGfwxSC7kwvfROY7cZ"]],[9,"Machine",5,[-30,-31,-32]],[21,"M_0_1",7,[[0,"WB_1",-34,[1,1,0,0]],[0,"WB_2",-35,[1,2,0,0]]],[[18,-33]],[1,3,0,-1.5],[3,0,-0.7071067811865475,0,0.7071067811865476],[1,0,-90,0]],[17,"M_1_1",7,[[0,"WB_1",-37,[1,1,0,0]],[0,"WB_2",-38,[1,2,0,0]]],[[18,-36]],[1,-1,0,-1.5]],[21,"M_2_1",7,[[0,"WB_1",-40,[1,-1,0,0]],[0,"WB_2",-41,[1,-2,0,0]]],[[18,-39]],[1,-3,0,-1.5],[3,0,0.7071067811865475,0,0.7071067811865476],[1,0,90,0]],[22,"Start",[[0,"End",-44,[1,-12,0,0]]],[[16,-42],[24,-43]],[1,6,0,5.5]],[22,"Start",[[0,"End",-47,[1,12,0,0]]],[[16,-45],[24,-46]],[1,-6,0,6.5]],[31,"CameraRange","d7kxzoNS9BkbdK1aiQpvKY",3,[-50],[[23,"Cube<ModelComponent>",-48,[9],[4],10],[49,-49]],[1,4.5,0,-5.265]],[32,0,null,[38,"e103AGfwxSC7kwvfROY7cZ",null,null,-54,[50,"9d2pBSW4xBVbJne3dUPoaQ",null,[[19,"Level3_Scence",["_name"],6],[20,["_lpos"],6,[1,0,0,0]],[20,["_lrot"],6,[3,0,0,0,1]],[20,["_euler"],6,[1,0,0,0]],[51,["_materials","0"],-51,1],[15,["_materials","0"],[1,["a70TKS1dldZKdpAHws5h91"]],2],[15,["_materials","0"],[1,["c2BXncYG9VobZJHlVXrHL3"]],3],[15,["_materials","0"],[1,["a7oSkYTLhTTqcr5ZJobtrj"]],4],[12,["_lpos"],[1,["329dsfDy5fQqjIsBTm/ZhM"]],[1,0,0,0]],[15,["_materials","0"],[1,["88FltwsJZUAo3E3x6WykKq"]],5],[15,["_materials","0"],[1,["266lxKbAdQtb3jA6lI5VQC"]],6],[19,1,["_shadowCastingMode"],-52],[12,["_lpos"],[1,["dbyyMsDoVfwprh1T0XdMDj"]],[1,0,0,0]],[12,["_lpos"],[1,["641Zmjnl1YtL7pdvwi4US5"]],[1,0,0,0]],[12,["_lpos"],[1,["ecd/gFgEVbZo9C5TOVB/wv"]],[1,0,0,0]],[12,["_lpos"],[1,["ac34y8yYhV161zw6bhE6GX"]],[1,0,0,0]],[19,0,["_shadowReceivingMode"],-53],[12,["_lpos"],[1,["0dEiMpemRf+o65jMvQjbT6"]],[1,0,-0.5,0]]]],0]],[1,["4bUCtekHBZAbH7dB6ugq04"]],[7,"D_1",2,[[6,"get",-55,[1,0,0,1],[3,0,1,0,6.123233995736766e-17],[1,0,180,0]],[0,"put",-56,[1,0,0,-1]]],[1,3,-0.4,2.5]],[7,"D_1",2,[[6,"get",-57,[1,0,0,1],[3,0,1,0,6.123233995736766e-17],[1,0,180,0]],[0,"put",-58,[1,0,0,-1]]],[1,2,-0.4,2.5]],[7,"D_1",2,[[6,"get",-59,[1,0,0,1],[3,0,1,0,6.123233995736766e-17],[1,0,180,0]],[0,"put",-60,[1,0,0,-1]]],[1,1,-0.4,2.5]],[7,"D_1",2,[[6,"get",-61,[1,0,0,1],[3,0,1,0,6.123233995736766e-17],[1,0,180,0]],[0,"put",-62,[1,0,0,-1]]],[1,0,-0.4,2.5]],[7,"D_1",2,[[6,"get",-63,[1,0,0,1],[3,0,1,0,6.123233995736766e-17],[1,0,180,0]],[0,"put",-64,[1,0,0,-1]]],[1,-1,-0.4,2.5]],[7,"D_1",2,[[6,"get",-65,[1,0,0,1],[3,0,1,0,6.123233995736766e-17],[1,0,180,0]],[0,"put",-66,[1,0,0,-1]]],[1,-2,-0.4,2.5]],[7,"D_1",2,[[6,"get",-67,[1,0,0,1],[3,0,1,0,6.123233995736766e-17],[1,0,180,0]],[0,"put",-68,[1,0,0,-1]]],[1,-3,-0.4,2.5]],[9,"Spawn",5,[-69,-70]],[9,"Customer",23,[11,12]],[9,"Nobody",5,[-71,-72]],[17,"Start",25,[[0,"End",-74,[1,-11.96,0,0]]],[[16,-73]],[1,7.799,0,9.5]],[17,"Start",25,[[0,"End",-76,[1,12.467,0,0]]],[[16,-75]],[1,-7.208,0,10.5]],[2,"MapGrid",4,[[52,-78,-77,[0,13,9]]],[1,-6,0,-1.5]],[33,"CameraRoot-001","7f5u0B3A5E+5IzqU+RVN4C",3,[-80],[[53,-79]],[1,0,0,-5.456],[3,0,1,0,6.123233995736766e-17],[1,0,180,0]],[34,"MainCamera",29,[[54,0,60,0,1822425087,-81],[55,-82]],[1,0,16,16],[3,-0.3826834323650898,3.8238333496938364e-33,1.4925397554429303e-32,0.9238795325112867],[1,-45,1.059337511532038e-30,1.4124500153760508e-30]],[35,"Main Light","c0y6F5f+pAvI805TdmxIjx",3,[[56,-83,[4,4293982975],[57]]],[3,0.10808857162696617,-0.6005809499994564,-0.749082992700597,-0.25786440861063],[1,-98.665,-209.209,14.862]],[9,"Env",4,[14]],[2,"Obstacle-001",1,[[3,-84]],[1,4,0,1.5]],[2,"Obstacle-002",1,[[3,-85]],[1,4,0,2.5]],[2,"Obstacle-003",1,[[3,-86]],[1,4,0,3.5]],[2,"Obstacle-004",1,[[3,-87]],[1,5,0,3.5]],[2,"Obstacle-005",1,[[3,-88]],[1,6,0,3.5]],[2,"Obstacle-006",1,[[3,-89]],[1,-4,0,1.5]],[2,"Obstacle-007",1,[[3,-90]],[1,-4,0,2.5]],[2,"Obstacle-008",1,[[3,-91]],[1,-4,0,3.5]],[2,"Obstacle-009",1,[[3,-92]],[1,-5,0,3.5]],[2,"Obstacle-010",1,[[3,-93]],[1,-6,0,3.5]],[36,"Staff_1",23,[[58,-94]]],[2,"End",13,[[23,"Cube<ModelComponent>",-95,[7],[4],8]],[1,-9,0,18.556]]],0,[0,-1,33,0,-2,34,0,-3,35,0,-4,36,0,-5,37,0,-6,38,0,-7,39,0,-8,40,0,-9,41,0,-10,42,0,0,2,0,-1,16,0,-2,17,0,-3,18,0,-4,19,0,-5,20,0,-6,21,0,-7,22,0,-1,14,0,-1,31,0,-2,4,0,-3,13,0,-4,29,0,-1,32,0,-3,5,0,-4,28,0,-1,7,0,-3,23,0,-4,25,0,-1,8,0,-2,9,0,-3,10,0,0,8,0,1,8,0,1,8,0,0,9,0,1,9,0,1,9,0,0,10,0,1,10,0,1,10,0,0,11,0,0,11,0,1,11,0,0,12,0,0,12,0,1,12,0,0,13,0,0,13,0,-1,44,0,6,15,0,6,15,0,6,15,0,8,14,0,1,16,0,1,16,0,1,17,0,1,17,0,1,18,0,1,18,0,1,19,0,1,19,0,1,20,0,1,20,0,1,21,0,1,21,0,1,22,0,1,22,0,-1,43,0,-2,24,0,-1,26,0,-2,27,0,0,26,0,1,26,0,0,27,0,1,27,0,10,28,0,0,28,0,0,29,0,-1,30,0,0,30,0,0,30,0,0,31,0,0,33,0,0,34,0,0,35,0,0,36,0,0,37,0,0,38,0,0,39,0,0,40,0,0,41,0,0,42,0,0,43,0,0,44,0,11,3,1,1,4,2,1,5,11,1,24,12,1,24,14,1,32,95],[0,0,0,0,0,0,0,0,0,0,0],[12,3,3,3,3,3,3,-1,2,-1,2],[15,16,3,3,17,18,19,4,5,4,5]]]]
